Workbook

Sheet Start here
A1: Sprint 53 - Set B translation review (English → Mandarin)
A3: What you are doing | B3: Checking translations we wrote to test automatic (LLM) translation judges. For each row, tell us if the row is what it claims to be, and what quality band you would give it. Read SetB_Reviewer_Instructions.docx first (about 10 minutes).
A4: Rows to review | B4: 265 rows on the 'Review' tab, grouped by English sentence (40 sentences). Expect about 1 minute per row; it is fine to work in several sittings.
A5: Where to type | B5: ONLY in the yellow columns M-R. Grey and white columns are pre-filled - please do not edit them. Column S fills itself in.
A6: Q1 Row matches its description? | B6: Yes / No / Partly / Not sure. Column I says what the row is supposed to be.
A7: Q2 Your quality band | B7: clean / moderate / poor - your own judgement of the candidate (definitions below).
A8: Q3 Planted error severity | B8: Only for rows with a planted error (columns J-K): minor / major / critical, or 'not an error' if you think it is actually acceptable. 'n/a' is pre-filled where there is no planted error.
A9: Q4 Other errors | B9: Any error we did not plant or describe. Quote the Chinese text and say why.
A10: Q5 Suggested correction | B10: Only if the row is wrong for its purpose. Write the FULL corrected sentence. For gold rows this becomes the new reference.
A11: Band: clean | B11: Correct meaning, natural Chinese. You would publish it with at most tiny edits.
A12: Band: moderate | B12: Meaning is essentially right, but it is stiff, unnatural, slightly off in tone, or has small errors a reader would notice.
A13: Band: poor | B13: At least one meaning error that would mislead a reader, or the sentence does not make sense.
A14: Traditional-script rows | B14: You are not expected to be a Traditional-script expert. Check the meaning; answer 'Not sure' in Q1 about Taiwan word choice if unfamiliar.
A15: When finished | B15: Save the file with your initials in the name (e.g. SetB_Review_Workbook_LW.xlsx) and send it back. The 'Summary' tab shows your progress.
A17: Example of a completed row
A18: Row type | B18: fluent_wrong
A19: English source | B19: The museum opens at nine every morning.
A20: Candidate translation | B20: 博物馆每天晚上九点开门。
A21: Planted error | B21: 晚上 - [Mistranslation, major] 'Morning' becomes 'evening'.
A22: Q1. Row matches its description? | B22: Yes
A23: Q2. Your quality band | B23: poor
A24: Q3. Planted error severity | B24: major
A25: Q4. Other errors you found | B25: (blank - none)
A26: Q5. Suggested correction | B26: (blank - the error is intentional, do not correct it)
A27: Comments | B27: Reads naturally, so a careless reader would be misled.

Sheet Review
A1: item_id | B1: Source ID | C1: Category | D1: Row type | E1: Script | F1: English source | G1: Candidate translation (CHECK THIS) | H1: Gold reference (for comparison) | I1: What this row is supposed to be | J1: Planted error - text | K1: Planted error - what is wrong | L1: Our expected band | M1: Q1. Row matches its description? | N1: Q2. Your quality band | O1: Q3. Planted error severity | P1: Q4. Other errors you found | Q1: Q5. Suggested correction (full sentence) | R1: Comments | S1: Band agrees? (auto)
A2: B::S52_001::gold | B2: S52_001 | C2: simple_control | D2: gold | E2: simplified | F2: Let's try it. | G2: 我们试试吧。 | H2: 我们试试吧。 | I2: PROPOSED REFERENCE. Should be a fully correct, natural Mainland Mandarin translation. If anything is wrong or unnatural, write a corrected sentence in column Q - it will become the reference for every row of this source. | L2: clean | M2: Yes | N2: clean | O2: n/a | S2: =IF(N2="","",IF(N2=L2,"agree","DISAGREE")) -> agree
A3: B::S52_001::paraphrase | B3: S52_001 | C3: simple_control | D3: paraphrase | E3: simplified | F3: Let's try it. | G3: 咱们来试一下。 | H3: 我们试试吧。 | I3: Should mean EXACTLY the same as the gold row, using deliberately different wording. Check nothing is added, lost or changed, and that it sounds natural. | L3: clean | M3: Yes | N3: clean | O3: n/a | S3: =IF(N3="","",IF(N3=L3,"agree","DISAGREE")) -> agree
A4: B::S52_001::literal | B4: S52_001 | C4: simple_control | D4: literal | E4: simplified | F4: Let's try it. | G4: 让我们尝试它。 | H4: 我们试试吧。 | I4: Should have NO meaning errors, but be stiff / word-for-word on purpose. Stiffness is intended - only flag meaning problems or ungrammatical Chinese. | L4: moderate | M4: Yes | N4: moderate | O4: n/a | S4: =IF(N4="","",IF(N4=L4,"agree","DISAGREE")) -> agree
A5: B::S52_001::fluent_wrong | B5: S52_001 | C5: simple_control | D5: fluent_wrong | E5: simplified | F5: Let's try it. | G5: 我们别试了吧。 | H5: 我们试试吧。 | I5: Should read naturally but contain exactly ONE planted meaning error (columns J-K). Check the error is real and that there is no OTHER error. | J5: 别试了 | K5: [Mistranslation, major] Suggestion to try becomes suggestion NOT to try (polarity reversed). | L5: poor | M5: Yes | N5: poor | O5: major | S5: =IF(N5="","",IF(N5=L5,"agree","DISAGREE")) -> agree
A6: B::S52_001::targeted_error | B6: S52_001 | C6: simple_control | D6: targeted_error | E6: simplified | F6: Let's try it. | G6: 我们已经试过了。 | H6: 我们试试吧。 | I6: Contains exactly ONE planted error typical of this category (columns J-K). Check the error is real and that there is no OTHER error. | J6: 已经试过了 | K6: [Mistranslation, major] Proposal ('let's try') becomes a statement about the past ('we already tried'). | L6: poor | M6: Yes | N6: poor | O6: major | S6: =IF(N6="","",IF(N6=L6,"agree","DISAGREE")) -> agree
A7: B::S52_001::original_candidate | B7: S52_001 | C7: simple_control | D7: original_candidate | E7: simplified | F7: Let's try it. | G7: 我们试一下吧。 | H7: 我们试试吧。 | I7: Existing Sprint 52 machine translation, not written for this sprint. We only need your quality band and any errors you see. | L7: clean | M7: Yes | N7: clean | O7: n/a | S7: =IF(N7="","",IF(N7=L7,"agree","DISAGREE")) -> agree
A8: B::S52_002::gold | B8: S52_002 | C8: simple_control | D8: gold | E8: simplified | F8: I have to go to sleep. | G8: 我得去睡觉了。 | H8: 我得去睡觉了。 | I8: PROPOSED REFERENCE. Should be a fully correct, natural Mainland Mandarin translation. If anything is wrong or unnatural, write a corrected sentence in column Q - it will become the reference for every row of this source. | L8: clean | M8: Yes | N8: clean | O8: n/a | S8: =IF(N8="","",IF(N8=L8,"agree","DISAGREE")) -> agree
A9: B::S52_002::paraphrase | B9: S52_002 | C9: simple_control | D9: paraphrase | E9: simplified | F9: I have to go to sleep. | G9: 我必须上床休息了。 | H9: 我得去睡觉了。 | I9: Should mean EXACTLY the same as the gold row, using deliberately different wording. Check nothing is added, lost or changed, and that it sounds natural. | L9: clean | M9: Yes | N9: clean | O9: n/a | S9: =IF(N9="","",IF(N9=L9,"agree","DISAGREE")) -> agree
A10: B::S52_002::literal | B10: S52_002 | C10: simple_control | D10: literal | E10: simplified | F10: I have to go to sleep. | G10: 我有去睡觉的必要。 | H10: 我得去睡觉了。 | I10: Should have NO meaning errors, but be stiff / word-for-word on purpose. Stiffness is intended - only flag meaning problems or ungrammatical Chinese. | L10: moderate | M10: Yes | N10: moderate | O10: n/a | S10: =IF(N10="","",IF(N10=L10,"agree","DISAGREE")) -> agree
A11: B::S52_002::fluent_wrong | B11: S52_002 | C11: simple_control | D11: fluent_wrong | E11: simplified | F11: I have to go to sleep. | G11: 我不想去睡觉。 | H11: 我得去睡觉了。 | I11: Should read naturally but contain exactly ONE planted meaning error (columns J-K). Check the error is real and that there is no OTHER error. | J11: 不想 | K11: [Mistranslation, major] 'Have to' becomes 'don't want to'. | L11: poor | M11: Yes | N11: poor | O11: major | S11: =IF(N11="","",IF(N11=L11,"agree","DISAGREE")) -> agree
A12: B::S52_002::targeted_error | B12: S52_002 | C12: simple_control | D12: targeted_error | E12: simplified | F12: I have to go to sleep. | G12: 我得去上班了。 | H12: 我得去睡觉了。 | I12: Contains exactly ONE planted error typical of this category (columns J-K). Check the error is real and that there is no OTHER error. | J12: 上班 | K12: [Mistranslation, major] 'Sleep' becomes 'go to work'. | L12: poor | M12: Yes | N12: poor | O12: major | S12: =IF(N12="","",IF(N12=L12,"agree","DISAGREE")) -> agree
A13: B::S52_002::original_candidate | B13: S52_002 | C13: simple_control | D13: original_candidate | E13: simplified | F13: I have to go to sleep. | G13: 我得去睡觉了。 | H13: 我得去睡觉了。 | I13: Existing Sprint 52 machine translation, not written for this sprint. We only need your quality band and any errors you see. | L13: clean | M13: Yes | N13: clean | O13: n/a | S13: =IF(N13="","",IF(N13=L13,"agree","DISAGREE")) -> agree
A14: B::S52_005::gold | B14: S52_005 | C14: simple_control | D14: gold | E14: simplified | F14: I will be back soon. | G14: 我很快就回来。 | H14: 我很快就回来。 | I14: PROPOSED REFERENCE. Should be a fully correct, natural Mainland Mandarin translation. If anything is wrong or unnatural, write a corrected sentence in column Q - it will become the reference for every row of this source. | L14: clean | M14: Yes | N14: clean | O14: n/a | S14: =IF(N14="","",IF(N14=L14,"agree","DISAGREE")) -> agree
A15: B::S52_005::paraphrase | B15: S52_005 | C15: simple_control | D15: paraphrase | E15: simplified | F15: I will be back soon. | G15: 我去去就来。 | H15: 我很快就回来。 | I15: Should mean EXACTLY the same as the gold row, using deliberately different wording. Check nothing is added, lost or changed, and that it sounds natural. | L15: clean | M15: Yes | N15: clean | O15: n/a | S15: =IF(N15="","",IF(N15=L15,"agree","DISAGREE")) -> agree
A16: B::S52_005::literal | B16: S52_005 | C16: simple_control | D16: literal | E16: simplified | F16: I will be back soon. | G16: 我将会很快地回来。 | H16: 我很快就回来。 | I16: Should have NO meaning errors, but be stiff / word-for-word on purpose. Stiffness is intended - only flag meaning problems or ungrammatical Chinese. | L16: moderate | M16: Yes | N16: moderate | O16: n/a | S16: =IF(N16="","",IF(N16=L16,"agree","DISAGREE")) -> agree
A17: B::S52_005::fluent_wrong | B17: S52_005 | C17: simple_control | D17: fluent_wrong | E17: simplified | F17: I will be back soon. | G17: 我很快就走。 | H17: 我很快就回来。 | I17: Should read naturally but contain exactly ONE planted meaning error (columns J-K). Check the error is real and that there is no OTHER error. | J17: 走 | K17: [Mistranslation, major] 'Be back' becomes 'leave'. | L17: poor | M17: Yes | N17: poor | O17: major | S17: =IF(N17="","",IF(N17=L17,"agree","DISAGREE")) -> agree
A18: B::S52_005::targeted_error | B18: S52_005 | C18: simple_control | D18: targeted_error | E18: simplified | F18: I will be back soon. | G18: 我明天就回来。 | H18: 我很快就回来。 | I18: Contains exactly ONE planted error typical of this category (columns J-K). Check the error is real and that there is no OTHER error. | J18: 明天 | K18: [Mistranslation, major] 'Soon' becomes 'tomorrow'. | L18: poor | M18: Yes | N18: poor | O18: major | S18: =IF(N18="","",IF(N18=L18,"agree","DISAGREE")) -> agree
A19: B::S52_005::original_candidate | B19: S52_005 | C19: simple_control | D19: original_candidate | E19: simplified | F19: I will be back soon. | G19: 我很快就会回来。 | H19: 我很快就回来。 | I19: Existing Sprint 52 machine translation, not written for this sprint. We only need your quality band and any errors you see. | L19: clean | M19: Yes | N19: clean | O19: n/a | S19: =IF(N19="","",IF(N19=L19,"agree","DISAGREE")) -> agree
A20: B::S52_008::gold | B20: S52_008 | C20: simple_control | D20: gold | E20: simplified | F20: Our flight was delayed because of the storm. | G20: 因为暴风雨，我们的航班延误了。 | H20: 因为暴风雨，我们的航班延误了。 | I20: PROPOSED REFERENCE. Should be a fully correct, natural Mainland Mandarin translation. If anything is wrong or unnatural, write a corrected sentence in column Q - it will become the reference for every row of this source. | L20: clean | M20: Yes | N20: clean | O20: n/a | S20: =IF(N20="","",IF(N20=L20,"agree","DISAGREE")) -> agree
A21: B::S52_008::paraphrase | B21: S52_008 | C21: simple_control | D21: paraphrase | E21: simplified | F21: Our flight was delayed because of the storm. | G21: 受风暴影响，我们的班机晚点了。 | H21: 因为暴风雨，我们的航班延误了。 | I21: Should mean EXACTLY the same as the gold row, using deliberately different wording. Check nothing is added, lost or changed, and that it sounds natural. | L21: clean | M21: Yes | N21: clean | O21: n/a | S21: =IF(N21="","",IF(N21=L21,"agree","DISAGREE")) -> agree
A22: B::S52_008::literal | B22: S52_008 | C22: simple_control | D22: literal | E22: simplified | F22: Our flight was delayed because of the storm. | G22: 我们的航班被延误了因为暴风雨。 | H22: 因为暴风雨，我们的航班延误了。 | I22: Should have NO meaning errors, but be stiff / word-for-word on purpose. Stiffness is intended - only flag meaning problems or ungrammatical Chinese. | L22: moderate | M22: Yes | N22: moderate | O22: n/a | S22: =IF(N22="","",IF(N22=L22,"agree","DISAGREE")) -> agree
A23: B::S52_008::padded | B23: S52_008 | C23: simple_control | D23: padded | E23: simplified | F23: Our flight was delayed because of the storm. | G23: 由于遇上了暴风雨天气的原因，我们所乘坐的这趟航班最终出现了延误的情况。 | H23: 因为暴风雨，我们的航班延误了。 | I23: Same meaning as gold, deliberately wordy/redundant. Check no meaning was added or lost. | L23: clean | M23: Yes | N23: clean | O23: n/a | S23: =IF(N23="","",IF(N23=L23,"agree","DISAGREE")) -> agree
A24: B::S52_008::fluent_wrong | B24: S52_008 | C24: simple_control | D24: fluent_wrong | E24: simplified | F24: Our flight was delayed because of the storm. | G24: 因为暴风雨，我们的航班取消了。 | H24: 因为暴风雨，我们的航班延误了。 | I24: Should read naturally but contain exactly ONE planted meaning error (columns J-K). Check the error is real and that there is no OTHER error. | J24: 取消 | K24: [Mistranslation, major] 'Delayed' becomes 'cancelled'. | L24: poor | M24: Yes | N24: poor | O24: major | S24: =IF(N24="","",IF(N24=L24,"agree","DISAGREE")) -> agree
A25: B::S52_008::targeted_error | B25: S52_008 | C25: simple_control | D25: targeted_error | E25: simplified | F25: Our flight was delayed because of the storm. | G25: 因为暴风雪，我们的航班延误了。 | H25: 因为暴风雨，我们的航班延误了。 | I25: Contains exactly ONE planted error typical of this category (columns J-K). Check the error is real and that there is no OTHER error. | J25: 暴风雪 | K25: [Mistranslation, major] 'Storm' becomes 'snowstorm/blizzard'. | L25: poor | M25: Yes | N25: poor | O25: major | S25: =IF(N25="","",IF(N25=L25,"agree","DISAGREE")) -> agree
A26: B::S52_008::original_candidate | B26: S52_008 | C26: simple_control | D26: original_candidate | E26: simplified | F26: Our flight was delayed because of the storm. | G26: 我们的航班因为暴风雨延误了。 | H26: 因为暴风雨，我们的航班延误了。 | I26: Existing Sprint 52 machine translation, not written for this sprint. We only need your quality band and any errors you see. | L26: clean | M26: Yes | N26: clean | O26: n/a | S26: =IF(N26="","",IF(N26=L26,"agree","DISAGREE")) -> agree
A27: B::S52_006::gold | B27: S52_006 | C27: numbers_units_dates | D27: gold | E27: simplified | F27: The museum opens at nine every morning. | G27: 博物馆每天早上九点开门。 | H27: 博物馆每天早上九点开门。 | I27: PROPOSED REFERENCE. Should be a fully correct, natural Mainland Mandarin translation. If anything is wrong or unnatural, write a corrected sentence in column Q - it will become the reference for every row of this source. | L27: clean | M27: Yes | N27: clean | O27: n/a | S27: =IF(N27="","",IF(N27=L27,"agree","DISAGREE")) -> agree
A28: B::S52_006::paraphrase | B28: S52_006 | C28: numbers_units_dates | D28: paraphrase | E28: simplified | F28: The museum opens at nine every morning. | G28: 这家博物馆每日上午9时开放。 | H28: 博物馆每天早上九点开门。 | I28: Should mean EXACTLY the same as the gold row, using deliberately different wording. Check nothing is added, lost or changed, and that it sounds natural. | L28: clean | M28: Yes | N28: clean | O28: n/a | S28: =IF(N28="","",IF(N28=L28,"agree","DISAGREE")) -> agree
A29: B::S52_006::literal | B29: S52_006 | C29: numbers_units_dates | D29: literal | E29: simplified | F29: The museum opens at nine every morning. | G29: 博物馆在每一个早晨的九点钟打开。 | H29: 博物馆每天早上九点开门。 | I29: Should have NO meaning errors, but be stiff / word-for-word on purpose. Stiffness is intended - only flag meaning problems or ungrammatical Chinese. | L29: moderate | M29: Yes | N29: moderate | O29: n/a | S29: =IF(N29="","",IF(N29=L29,"agree","DISAGREE")) -> agree
A30: B::S52_006::fluent_wrong | B30: S52_006 | C30: numbers_units_dates | D30: fluent_wrong | E30: simplified | F30: The museum opens at nine every morning. | G30: 博物馆每天晚上九点开门。 | H30: 博物馆每天早上九点开门。 | I30: Should read naturally but contain exactly ONE planted meaning error (columns J-K). Check the error is real and that there is no OTHER error. | J30: 晚上 | K30: [Mistranslation, major] 'Morning' becomes 'evening'. | L30: poor | M30: Yes | N30: poor | O30: major | S30: =IF(N30="","",IF(N30=L30,"agree","DISAGREE")) -> agree
A31: B::S52_006::targeted_error | B31: S52_006 | C31: numbers_units_dates | D31: targeted_error | E31: simplified | F31: The museum opens at nine every morning. | G31: 博物馆每天早上十点开门。 | H31: 博物馆每天早上九点开门。 | I31: Contains exactly ONE planted error typical of this category (columns J-K). Check the error is real and that there is no OTHER error. | J31: 十点 | K31: [Mistranslation, major] Nine o'clock becomes ten o'clock. | L31: poor | M31: Yes | N31: poor | O31: major | S31: =IF(N31="","",IF(N31=L31,"agree","DISAGREE")) -> agree
A32: B::S52_006::original_candidate | B32: S52_006 | C32: numbers_units_dates | D32: original_candidate | E32: simplified | F32: The museum opens at nine every morning. | G32: 博物馆每天早上九点开门。 | H32: 博物馆每天早上九点开门。 | I32: Existing Sprint 52 machine translation, not written for this sprint. We only need your quality band and any errors you see. | L32: clean | M32: Yes | N32: clean | O32: n/a | S32: =IF(N32="","",IF(N32=L32,"agree","DISAGREE")) -> agree
A33: B::S52_006::traditional_char | B33: S52_006 | C33: numbers_units_dates | D33: traditional_char | E33: traditional_char | F33: The museum opens at nine every morning. | G33: 博物館每天早上九點開門。 | H33: 博物馆每天早上九点开门。 | I33: Gold converted to Traditional CHARACTERS only - same words. Check the meaning is unchanged and characters look right (e.g. no wrong 裡/里 swaps in names). | L33: clean | M33: Yes | N33: clean | O33: n/a | S33: =IF(N33="","",IF(N33=L33,"agree","DISAGREE")) -> agree
A34: B::A_375::gold | B34: A_375 | C34: numbers_units_dates | D34: gold | E34: simplified | F34: A person who weighs 200 pounds (90kg) on Earth would weigh about 36 pounds (16kg) on Io. So the gravity, of course, pulls less on you. | G34: 一个在地球上重200磅（90千克）的人，到了木卫一上体重只有约36磅（16千克）。因此，那里的引力对你的拉力自然更小。 | H34: 一个在地球上重200磅（90千克）的人，到了木卫一上体重只有约36磅（16千克）。因此，那里的引力对你的拉力自然更小。 | I34: PROPOSED REFERENCE. Should be a fully correct, natural Mainland Mandarin translation. If anything is wrong or unnatural, write a corrected sentence in column Q - it will become the reference for every row of this source. | L34: clean | M34: Yes | N34: clean | O34: n/a | S34: =IF(N34="","",IF(N34=L34,"agree","DISAGREE")) -> agree
A35: B::A_375::paraphrase | B35: A_375 | C35: numbers_units_dates | D35: paraphrase | E35: simplified | F35: A person who weighs 200 pounds (90kg) on Earth would weigh about 36 pounds (16kg) on Io. So the gravity, of course, pulls less on you. | G35: 在地球上体重90公斤（200磅）的人，若站在木卫一上，体重约为16公斤（36磅）——很显然，那里的重力对人的牵引要小得多。 | H35: 一个在地球上重200磅（90千克）的人，到了木卫一上体重只有约36磅（16千克）。因此，那里的引力对你的拉力自然更小。 | I35: Should mean EXACTLY the same as the gold row, using deliberately different wording. Check nothing is added, lost or changed, and that it sounds natural. | L35: clean | M35: Yes | N35: clean | O35: n/a | S35: =IF(N35="","",IF(N35=L35,"agree","DISAGREE")) -> agree
A36: B::A_375::literal | B36: A_375 | C36: numbers_units_dates | D36: literal | E36: simplified | F36: A person who weighs 200 pounds (90kg) on Earth would weigh about 36 pounds (16kg) on Io. So the gravity, of course, pulls less on you. | G36: 一个在地球上称重200磅（90千克）的人，在木卫一上将称重大约36磅（16千克）。所以重力，当然，在你身上拉得更少。 | H36: 一个在地球上重200磅（90千克）的人，到了木卫一上体重只有约36磅（16千克）。因此，那里的引力对你的拉力自然更小。 | I36: Should have NO meaning errors, but be stiff / word-for-word on purpose. Stiffness is intended - only flag meaning problems or ungrammatical Chinese. | L36: moderate | M36: Yes | N36: moderate | O36: n/a | S36: =IF(N36="","",IF(N36=L36,"agree","DISAGREE")) -> agree
A37: B::A_375::fluent_wrong | B37: A_375 | C37: numbers_units_dates | D37: fluent_wrong | E37: simplified | F37: A person who weighs 200 pounds (90kg) on Earth would weigh about 36 pounds (16kg) on Io. So the gravity, of course, pulls less on you. | G37: 一个在地球上重200磅（90千克）的人，到了木卫一上体重只有约36磅（16千克）。因此，那里的引力对你的拉力自然更大。 | H37: 一个在地球上重200磅（90千克）的人，到了木卫一上体重只有约36磅（16千克）。因此，那里的引力对你的拉力自然更小。 | I37: Should read naturally but contain exactly ONE planted meaning error (columns J-K). Check the error is real and that there is no OTHER error. | J37: 更大 | K37: [Mistranslation, major] Gravity pulls 'less' becomes 'more'. | L37: poor | M37: Yes | N37: poor | O37: major | S37: =IF(N37="","",IF(N37=L37,"agree","DISAGREE")) -> agree
A38: B::A_375::targeted_error | B38: A_375 | C38: numbers_units_dates | D38: targeted_error | E38: simplified | F38: A person who weighs 200 pounds (90kg) on Earth would weigh about 36 pounds (16kg) on Io. So the gravity, of course, pulls less on you. | G38: 一个在地球上重200磅（90千克）的人，到了木卫一上体重只有约36千克（16磅）。因此，那里的引力对你的拉力自然更小。 | H38: 一个在地球上重200磅（90千克）的人，到了木卫一上体重只有约36磅（16千克）。因此，那里的引力对你的拉力自然更小。 | I38: Contains exactly ONE planted error typical of this category (columns J-K). Check the error is real and that there is no OTHER error. | J38: 36千克（16磅） | K38: [Mistranslation, major] Units swapped: 36 pounds (16 kg) becomes 36 kg (16 pounds). | L38: poor | M38: Yes | N38: poor | O38: major | S38: =IF(N38="","",IF(N38=L38,"agree","DISAGREE")) -> agree
A39: B::A_375::traditional_char | B39: A_375 | C39: numbers_units_dates | D39: traditional_char | E39: traditional_char | F39: A person who weighs 200 pounds (90kg) on Earth would weigh about 36 pounds (16kg) on Io. So the gravity, of course, pulls less on you. | G39: 一個在地球上重200磅（90千克）的人，到了木衛一上體重只有約36磅（16千克）。因此，那裡的引力對你的拉力自然更小。 | H39: 一个在地球上重200磅（90千克）的人，到了木卫一上体重只有约36磅（16千克）。因此，那里的引力对你的拉力自然更小。 | I39: Gold converted to Traditional CHARACTERS only - same words. Check the meaning is unchanged and characters look right (e.g. no wrong 裡/里 swaps in names). | L39: clean | M39: Yes | N39: clean | O39: n/a | S39: =IF(N39="","",IF(N39=L39,"agree","DISAGREE")) -> agree
A40: B::A_375::traditional_tw | B40: A_375 | C40: numbers_units_dates | D40: traditional_tw | E40: traditional_tw | F40: A person who weighs 200 pounds (90kg) on Earth would weigh about 36 pounds (16kg) on Io. So the gravity, of course, pulls less on you. | G40: 一個在地球上重200磅（90公斤）的人，到了木衛一上體重只有約36磅（16公斤）。因此，那裡的引力對你的拉力自然更小。 | H40: 一个在地球上重200磅（90千克）的人，到了木卫一上体重只有约36磅（16千克）。因此，那里的引力对你的拉力自然更小。 | I40: Gold adapted for Taiwan: Traditional characters + Taiwan vocabulary (e.g. 伺服器, 公尺, 財務長) + 「」 quotes. Check the meaning is unchanged. If you are unsure whether a word is natural in Taiwan, answer 'Not sure' in Q1 rather than guessing. | L40: clean | M40: Yes | N40: clean | O40: n/a | S40: =IF(N40="","",IF(N40=L40,"agree","DISAGREE")) -> agree
A41: B::A_43::gold | B41: A_43 | C41: numbers_units_dates | D41: gold | E41: simplified | F41: The storm, situated about 645 miles (1040 km) west of the Cape Verde islands, is likely to dissipate before threatening any land areas, forecasters say. | G41: 预报员称，这场风暴位于佛得角群岛以西约645英里（1040公里）处，很可能在对任何陆地构成威胁之前就会消散。 | H41: 预报员称，这场风暴位于佛得角群岛以西约645英里（1040公里）处，很可能在对任何陆地构成威胁之前就会消散。 | I41: PROPOSED REFERENCE. Should be a fully correct, natural Mainland Mandarin translation. If anything is wrong or unnatural, write a corrected sentence in column Q - it will become the reference for every row of this source. | L41: clean | M41: Yes | N41: clean | O41: n/a | S41: =IF(N41="","",IF(N41=L41,"agree","DISAGREE")) -> agree
A42: B::A_43::paraphrase | B42: A_43 | C42: numbers_units_dates | D42: paraphrase | E42: simplified | F42: The storm, situated about 645 miles (1040 km) west of the Cape Verde islands, is likely to dissipate before threatening any land areas, forecasters say. | G42: 据气象预报人员介绍，这个风暴目前位于佛得角群岛西侧约1040公里（645英里）的海面上，有望在威胁到陆地之前自行减弱消失。 | H42: 预报员称，这场风暴位于佛得角群岛以西约645英里（1040公里）处，很可能在对任何陆地构成威胁之前就会消散。 | I42: Should mean EXACTLY the same as the gold row, using deliberately different wording. Check nothing is added, lost or changed, and that it sounds natural. | L42: clean | M42: Yes | N42: clean | O42: n/a | S42: =IF(N42="","",IF(N42=L42,"agree","DISAGREE")) -> agree
A43: B::A_43::literal | B43: A_43 | C43: numbers_units_dates | D43: literal | E43: simplified | F43: The storm, situated about 645 miles (1040 km) west of the Cape Verde islands, is likely to dissipate before threatening any land areas, forecasters say. | G43: 这场风暴，位于大约645英里（1040公里）在佛得角群岛的西边，很可能在威胁任何陆地地区之前消散，预报员们说。 | H43: 预报员称，这场风暴位于佛得角群岛以西约645英里（1040公里）处，很可能在对任何陆地构成威胁之前就会消散。 | I43: Should have NO meaning errors, but be stiff / word-for-word on purpose. Stiffness is intended - only flag meaning problems or ungrammatical Chinese. | L43: moderate | M43: Yes | N43: moderate | O43: n/a | S43: =IF(N43="","",IF(N43=L43,"agree","DISAGREE")) -> agree
A44: B::A_43::fluent_wrong | B44: A_43 | C44: numbers_units_dates | D44: fluent_wrong | E44: simplified | F44: The storm, situated about 645 miles (1040 km) west of the Cape Verde islands, is likely to dissipate before threatening any land areas, forecasters say. | G44: 预报员称，这场风暴位于佛得角群岛以西约645英里（1040公里）处，很可能在对陆地构成威胁之后才会消散。 | H44: 预报员称，这场风暴位于佛得角群岛以西约645英里（1040公里）处，很可能在对任何陆地构成威胁之前就会消散。 | I44: Should read naturally but contain exactly ONE planted meaning error (columns J-K). Check the error is real and that there is no OTHER error. | J44: 之后才会 | K44: [Mistranslation, major] Dissipate 'before' threatening land becomes 'after'. | L44: poor | M44: Yes | N44: poor | O44: major | S44: =IF(N44="","",IF(N44=L44,"agree","DISAGREE")) -> agree
A45: B::A_43::targeted_error | B45: A_43 | C45: numbers_units_dates | D45: targeted_error | E45: simplified | F45: The storm, situated about 645 miles (1040 km) west of the Cape Verde islands, is likely to dissipate before threatening any land areas, forecasters say. | G45: 预报员称，这场风暴位于佛得角群岛以西约465英里（1040公里）处，很可能在对任何陆地构成威胁之前就会消散。 | H45: 预报员称，这场风暴位于佛得角群岛以西约645英里（1040公里）处，很可能在对任何陆地构成威胁之前就会消散。 | I45: Contains exactly ONE planted error typical of this category (columns J-K). Check the error is real and that there is no OTHER error. | J45: 465英里 | K45: [Mistranslation, major] 645 miles becomes 465 miles (digits transposed). | L45: poor | M45: Yes | N45: poor | O45: major | S45: =IF(N45="","",IF(N45=L45,"agree","DISAGREE")) -> agree
A46: B::A_43::traditional_char | B46: A_43 | C46: numbers_units_dates | D46: traditional_char | E46: traditional_char | F46: The storm, situated about 645 miles (1040 km) west of the Cape Verde islands, is likely to dissipate before threatening any land areas, forecasters say. | G46: 預報員稱，這場風暴位於佛得角群島以西約645英里（1040公里）處，很可能在對任何陸地構成威脅之前就會消散。 | H46: 预报员称，这场风暴位于佛得角群岛以西约645英里（1040公里）处，很可能在对任何陆地构成威胁之前就会消散。 | I46: Gold converted to Traditional CHARACTERS only - same words. Check the meaning is unchanged and characters look right (e.g. no wrong 裡/里 swaps in names). | L46: clean | M46: Yes | N46: clean | O46: n/a | S46: =IF(N46="","",IF(N46=L46,"agree","DISAGREE")) -> agree
A47: B::A_43::traditional_tw | B47: A_43 | C47: numbers_units_dates | D47: traditional_tw | E47: traditional_tw | F47: The storm, situated about 645 miles (1040 km) west of the Cape Verde islands, is likely to dissipate before threatening any land areas, forecasters say. | G47: 預報員稱，這場風暴位於維德角群島以西約645英里（1040公里）處，很可能在對任何陸地構成威脅之前就會消散。 | H47: 预报员称，这场风暴位于佛得角群岛以西约645英里（1040公里）处，很可能在对任何陆地构成威胁之前就会消散。 | I47: Gold adapted for Taiwan: Traditional characters + Taiwan vocabulary (e.g. 伺服器, 公尺, 財務長) + 「」 quotes. Check the meaning is unchanged. If you are unsure whether a word is natural in Taiwan, answer 'Not sure' in Q1 rather than guessing. | L47: clean | M47: Yes | N47: clean | O47: n/a | S47: =IF(N47="","",IF(N47=L47,"agree","DISAGREE")) -> agree
A48: B::A_1741::gold | B48: A_1741 | C48: numbers_units_dates | D48: gold | E48: simplified | F48: The vertical clearance under the bridge is 15 meters. Construction was completed in August 2011, it didn't open to traffic until March 2017. | G48: 桥下的垂直净空为15米。大桥于2011年8月完工，但直到2017年3月才通车。 | H48: 桥下的垂直净空为15米。大桥于2011年8月完工，但直到2017年3月才通车。 | I48: PROPOSED REFERENCE. Should be a fully correct, natural Mainland Mandarin translation. If anything is wrong or unnatural, write a corrected sentence in column Q - it will become the reference for every row of this source. | L48: clean | M48: Yes | N48: clean | O48: n/a | S48: =IF(N48="","",IF(N48=L48,"agree","DISAGREE")) -> agree
A49: B::A_1741::paraphrase | B49: A_1741 | C49: numbers_units_dates | D49: paraphrase | E49: simplified | F49: The vertical clearance under the bridge is 15 meters. Construction was completed in August 2011, it didn't open to traffic until March 2017. | G49: 这座桥的桥下净高达15米；工程在2011年8月就已竣工，却一直拖到2017年3月才开放通行。 | H49: 桥下的垂直净空为15米。大桥于2011年8月完工，但直到2017年3月才通车。 | I49: Should mean EXACTLY the same as the gold row, using deliberately different wording. Check nothing is added, lost or changed, and that it sounds natural. | L49: clean | M49: Yes | N49: clean | O49: n/a | S49: =IF(N49="","",IF(N49=L49,"agree","DISAGREE")) -> agree
A50: B::A_1741::literal | B50: A_1741 | C50: numbers_units_dates | D50: literal | E50: simplified | F50: The vertical clearance under the bridge is 15 meters. Construction was completed in August 2011, it didn't open to traffic until March 2017. | G50: 在桥下面的垂直间隙是15米。建设在2011年8月被完成，它没有对交通开放直到2017年3月。 | H50: 桥下的垂直净空为15米。大桥于2011年8月完工，但直到2017年3月才通车。 | I50: Should have NO meaning errors, but be stiff / word-for-word on purpose. Stiffness is intended - only flag meaning problems or ungrammatical Chinese. | L50: moderate | M50: Yes | N50: moderate | O50: n/a | S50: =IF(N50="","",IF(N50=L50,"agree","DISAGREE")) -> agree
A51: B::A_1741::padded | B51: A_1741 | C51: numbers_units_dates | D51: padded | E51: simplified | F51: The vertical clearance under the bridge is 15 meters. Construction was completed in August 2011, it didn't open to traffic until March 2017. | G51: 这座桥梁桥下的垂直净空高度为15米。该座大桥的建设工程于2011年8月份正式宣告完工，但是却直到2017年3月份才最终开放通车。 | H51: 桥下的垂直净空为15米。大桥于2011年8月完工，但直到2017年3月才通车。 | I51: Same meaning as gold, deliberately wordy/redundant. Check no meaning was added or lost. | L51: clean | M51: Yes | N51: clean | O51: n/a | S51: =IF(N51="","",IF(N51=L51,"agree","DISAGREE")) -> agree
A52: B::A_1741::fluent_wrong | B52: A_1741 | C52: numbers_units_dates | D52: fluent_wrong | E52: simplified | F52: The vertical clearance under the bridge is 15 meters. Construction was completed in August 2011, it didn't open to traffic until March 2017. | G52: 桥下的垂直净空为15米。大桥于2011年8月动工，但直到2017年3月才通车。 | H52: 桥下的垂直净空为15米。大桥于2011年8月完工，但直到2017年3月才通车。 | I52: Should read naturally but contain exactly ONE planted meaning error (columns J-K). Check the error is real and that there is no OTHER error. | J52: 动工 | K52: [Mistranslation, major] Construction 'completed' becomes 'started'. | L52: poor | M52: Yes | N52: poor | O52: major | S52: =IF(N52="","",IF(N52=L52,"agree","DISAGREE")) -> agree
A53: B::A_1741::targeted_error | B53: A_1741 | C53: numbers_units_dates | D53: targeted_error | E53: simplified | F53: The vertical clearance under the bridge is 15 meters. Construction was completed in August 2011, it didn't open to traffic until March 2017. | G53: 桥下的垂直净空为15米。大桥于2011年8月完工，但直到2017年5月才通车。 | H53: 桥下的垂直净空为15米。大桥于2011年8月完工，但直到2017年3月才通车。 | I53: Contains exactly ONE planted error typical of this category (columns J-K). Check the error is real and that there is no OTHER error. | J53: 2017年5月 | K53: [Mistranslation, major] March 2017 becomes May 2017. | L53: poor | M53: Yes | N53: poor | O53: major | S53: =IF(N53="","",IF(N53=L53,"agree","DISAGREE")) -> agree
A54: B::A_1741::traditional_char | B54: A_1741 | C54: numbers_units_dates | D54: traditional_char | E54: traditional_char | F54: The vertical clearance under the bridge is 15 meters. Construction was completed in August 2011, it didn't open to traffic until March 2017. | G54: 橋下的垂直淨空為15米。大橋於2011年8月完工，但直到2017年3月才通車。 | H54: 桥下的垂直净空为15米。大桥于2011年8月完工，但直到2017年3月才通车。 | I54: Gold converted to Traditional CHARACTERS only - same words. Check the meaning is unchanged and characters look right (e.g. no wrong 裡/里 swaps in names). | L54: clean | M54: Yes | N54: clean | O54: n/a | S54: =IF(N54="","",IF(N54=L54,"agree","DISAGREE")) -> agree
A55: B::A_1741::traditional_tw | B55: A_1741 | C55: numbers_units_dates | D55: traditional_tw | E55: traditional_tw | F55: The vertical clearance under the bridge is 15 meters. Construction was completed in August 2011, it didn't open to traffic until March 2017. | G55: 橋下的垂直淨高為15公尺。大橋於2011年8月完工，但直到2017年3月才通車。 | H55: 桥下的垂直净空为15米。大桥于2011年8月完工，但直到2017年3月才通车。 | I55: Gold adapted for Taiwan: Traditional characters + Taiwan vocabulary (e.g. 伺服器, 公尺, 財務長) + 「」 quotes. Check the meaning is unchanged. If you are unsure whether a word is natural in Taiwan, answer 'Not sure' in Q1 rather than guessing. | L55: clean | M55: Yes | N55: clean | O55: n/a | S55: =IF(N55="","",IF(N55=L55,"agree","DISAGREE")) -> agree
A56: B::N_NUM1::gold | B56: N_NUM1 | C56: numbers_units_dates | D56: gold | E56: simplified | F56: The rent increased by 15% to $2,300 a month, effective October 1. | G56: 房租上涨了15%，涨至每月2300美元，自10月1日起生效。 | H56: 房租上涨了15%，涨至每月2300美元，自10月1日起生效。 | I56: PROPOSED REFERENCE. Should be a fully correct, natural Mainland Mandarin translation. If anything is wrong or unnatural, write a corrected sentence in column Q - it will become the reference for every row of this source. | L56: clean | M56: Yes | N56: clean | O56: n/a | S56: =IF(N56="","",IF(N56=L56,"agree","DISAGREE")) -> agree
A57: B::N_NUM1::paraphrase | B57: N_NUM1 | C57: numbers_units_dates | D57: paraphrase | E57: simplified | F57: The rent increased by 15% to $2,300 a month, effective October 1. | G57: 从10月1日开始，月租金上调百分之十五，达到2300美元。 | H57: 房租上涨了15%，涨至每月2300美元，自10月1日起生效。 | I57: Should mean EXACTLY the same as the gold row, using deliberately different wording. Check nothing is added, lost or changed, and that it sounds natural. | L57: clean | M57: Yes | N57: clean | O57: n/a | S57: =IF(N57="","",IF(N57=L57,"agree","DISAGREE")) -> agree
A58: B::N_NUM1::literal | B58: N_NUM1 | C58: numbers_units_dates | D58: literal | E58: simplified | F58: The rent increased by 15% to $2,300 a month, effective October 1. | G58: 房租增加了15%到每月2,300美元，有效于10月1日。 | H58: 房租上涨了15%，涨至每月2300美元，自10月1日起生效。 | I58: Should have NO meaning errors, but be stiff / word-for-word on purpose. Stiffness is intended - only flag meaning problems or ungrammatical Chinese. | L58: moderate | M58: Yes | N58: moderate | O58: n/a | S58: =IF(N58="","",IF(N58=L58,"agree","DISAGREE")) -> agree
A59: B::N_NUM1::fluent_wrong | B59: N_NUM1 | C59: numbers_units_dates | D59: fluent_wrong | E59: simplified | F59: The rent increased by 15% to $2,300 a month, effective October 1. | G59: 房租上涨了15%，涨至每年2300美元，自10月1日起生效。 | H59: 房租上涨了15%，涨至每月2300美元，自10月1日起生效。 | I59: Should read naturally but contain exactly ONE planted meaning error (columns J-K). Check the error is real and that there is no OTHER error. | J59: 每年 | K59: [Mistranslation, major] 'A month' becomes 'a year'. | L59: poor | M59: Yes | N59: poor | O59: major | S59: =IF(N59="","",IF(N59=L59,"agree","DISAGREE")) -> agree
A60: B::N_NUM1::targeted_error | B60: N_NUM1 | C60: numbers_units_dates | D60: targeted_error | E60: simplified | F60: The rent increased by 15% to $2,300 a month, effective October 1. | G60: 房租上涨了50%，涨至每月2300美元，自10月1日起生效。 | H60: 房租上涨了15%，涨至每月2300美元，自10月1日起生效。 | I60: Contains exactly ONE planted error typical of this category (columns J-K). Check the error is real and that there is no OTHER error. | J60: 50% | K60: [Mistranslation, major] 15% becomes 50%. | L60: poor | M60: Yes | N60: poor | O60: major | S60: =IF(N60="","",IF(N60=L60,"agree","DISAGREE")) -> agree
A61: B::N_NUM1::traditional_char | B61: N_NUM1 | C61: numbers_units_dates | D61: traditional_char | E61: traditional_char | F61: The rent increased by 15% to $2,300 a month, effective October 1. | G61: 房租上漲了15%，漲至每月2300美元，自10月1日起生效。 | H61: 房租上涨了15%，涨至每月2300美元，自10月1日起生效。 | I61: Gold converted to Traditional CHARACTERS only - same words. Check the meaning is unchanged and characters look right (e.g. no wrong 裡/里 swaps in names). | L61: clean | M61: Yes | N61: clean | O61: n/a | S61: =IF(N61="","",IF(N61=L61,"agree","DISAGREE")) -> agree
A62: B::S52_003::gold | B62: S52_003 | C62: named_entity | D62: gold | E62: simplified | F62: Muiriel is 20 now. | G62: 穆里尔现在二十岁了。 | H62: 穆里尔现在二十岁了。 | I62: PROPOSED REFERENCE. Should be a fully correct, natural Mainland Mandarin translation. If anything is wrong or unnatural, write a corrected sentence in column Q - it will become the reference for every row of this source. NOTE: Paraphrase deliberately uses a different but valid transliteration (穆瑞尔 vs 穆里尔) to test whether judges penalise transliteration variation. | L62: clean | M62: Yes | N62: clean | O62: n/a | S62: =IF(N62="","",IF(N62=L62,"agree","DISAGREE")) -> agree
A63: B::S52_003::paraphrase | B63: S52_003 | C63: named_entity | D63: paraphrase | E63: simplified | F63: Muiriel is 20 now. | G63: 穆瑞尔如今已年满二十。 | H63: 穆里尔现在二十岁了。 | I63: Should mean EXACTLY the same as the gold row, using deliberately different wording. Check nothing is added, lost or changed, and that it sounds natural. | L63: clean | M63: Yes | N63: clean | O63: n/a | S63: =IF(N63="","",IF(N63=L63,"agree","DISAGREE")) -> agree
A64: B::S52_003::literal | B64: S52_003 | C64: named_entity | D64: literal | E64: simplified | F64: Muiriel is 20 now. | G64: 穆里尔现在是二十岁。 | H64: 穆里尔现在二十岁了。 | I64: Should have NO meaning errors, but be stiff / word-for-word on purpose. Stiffness is intended - only flag meaning problems or ungrammatical Chinese. | L64: moderate | M64: Yes | N64: moderate | O64: n/a | S64: =IF(N64="","",IF(N64=L64,"agree","DISAGREE")) -> agree
A65: B::S52_003::fluent_wrong | B65: S52_003 | C65: named_entity | D65: fluent_wrong | E65: simplified | F65: Muiriel is 20 now. | G65: 穆里尔现在十二岁了。 | H65: 穆里尔现在二十岁了。 | I65: Should read naturally but contain exactly ONE planted meaning error (columns J-K). Check the error is real and that there is no OTHER error. | J65: 十二 | K65: [Mistranslation, major] Age 20 becomes 12. | L65: poor | M65: Yes | N65: poor | O65: major | S65: =IF(N65="","",IF(N65=L65,"agree","DISAGREE")) -> agree
A66: B::S52_003::targeted_error | B66: S52_003 | C66: named_entity | D66: targeted_error | E66: simplified | F66: Muiriel is 20 now. | G66: 穆勒现在二十岁了。 | H66: 穆里尔现在二十岁了。 | I66: Contains exactly ONE planted error typical of this category (columns J-K). Check the error is real and that there is no OTHER error. | J66: 穆勒 | K66: [Mistranslation, major] Name transliterated as a different name (Muiriel -> 'Müller'). | L66: poor | M66: Yes | N66: poor | O66: major | S66: =IF(N66="","",IF(N66=L66,"agree","DISAGREE")) -> agree
A67: B::S52_003::original_candidate | B67: S52_003 | C67: named_entity | D67: original_candidate | E67: simplified | F67: Muiriel is 20 now. | G67: 穆瑞尔现在二十岁了。 | H67: 穆里尔现在二十岁了。 | I67: Existing Sprint 52 machine translation, not written for this sprint. We only need your quality band and any errors you see. | L67: clean | M67: Yes | N67: clean | O67: n/a | S67: =IF(N67="","",IF(N67=L67,"agree","DISAGREE")) -> agree
A68: B::S52_003::traditional_char | B68: S52_003 | C68: named_entity | D68: traditional_char | E68: traditional_char | F68: Muiriel is 20 now. | G68: 穆里爾現在二十歲了。 | H68: 穆里尔现在二十岁了。 | I68: Gold converted to Traditional CHARACTERS only - same words. Check the meaning is unchanged and characters look right (e.g. no wrong 裡/里 swaps in names). | L68: clean | M68: Yes | N68: clean | O68: n/a | S68: =IF(N68="","",IF(N68=L68,"agree","DISAGREE")) -> agree
A69: B::S52_004::gold | B69: S52_004 | C69: named_entity | D69: gold | E69: simplified | F69: The password is "Muiriel". | G69: 密码是“Muiriel”。 | H69: 密码是“Muiriel”。 | I69: PROPOSED REFERENCE. Should be a fully correct, natural Mainland Mandarin translation. If anything is wrong or unnatural, write a corrected sentence in column Q - it will become the reference for every row of this source. | L69: clean | M69: Yes | N69: clean | O69: n/a | S69: =IF(N69="","",IF(N69=L69,"agree","DISAGREE")) -> agree
A70: B::S52_004::paraphrase | B70: S52_004 | C70: named_entity | D70: paraphrase | E70: simplified | F70: The password is "Muiriel". | G70: 口令为“Muiriel”。 | H70: 密码是“Muiriel”。 | I70: Should mean EXACTLY the same as the gold row, using deliberately different wording. Check nothing is added, lost or changed, and that it sounds natural. | L70: clean | M70: Yes | N70: clean | O70: n/a | S70: =IF(N70="","",IF(N70=L70,"agree","DISAGREE")) -> agree
A71: B::S52_004::literal | B71: S52_004 | C71: named_entity | D71: literal | E71: simplified | F71: The password is "Muiriel". | G71: 那个密码是“Muiriel”。 | H71: 密码是“Muiriel”。 | I71: Should have NO meaning errors, but be stiff / word-for-word on purpose. Stiffness is intended - only flag meaning problems or ungrammatical Chinese. | L71: moderate | M71: Yes | N71: moderate | O71: n/a | S71: =IF(N71="","",IF(N71=L71,"agree","DISAGREE")) -> agree
A72: B::S52_004::fluent_wrong | B72: S52_004 | C72: named_entity | D72: fluent_wrong | E72: simplified | F72: The password is "Muiriel". | G72: 密码不是“Muiriel”。 | H72: 密码是“Muiriel”。 | I72: Should read naturally but contain exactly ONE planted meaning error (columns J-K). Check the error is real and that there is no OTHER error. | J72: 不是 | K72: [Mistranslation, major] Statement negated. | L72: poor | M72: Yes | N72: poor | O72: major | S72: =IF(N72="","",IF(N72=L72,"agree","DISAGREE")) -> agree
A73: B::S52_004::targeted_error | B73: S52_004 | C73: named_entity | D73: targeted_error | E73: simplified | F73: The password is "Muiriel". | G73: 密码是“穆里尔”。 | H73: 密码是“Muiriel”。 | I73: Contains exactly ONE planted error typical of this category (columns J-K). Check the error is real and that there is no OTHER error. | J73: 穆里尔 | K73: [Mistranslation, critical] A password must stay verbatim; transliterating it makes the information unusable. | L73: poor | M73: Yes | N73: poor | O73: critical | S73: =IF(N73="","",IF(N73=L73,"agree","DISAGREE")) -> agree
A74: B::S52_004::original_candidate | B74: S52_004 | C74: named_entity | D74: original_candidate | E74: simplified | F74: The password is "Muiriel". | G74: 密码是"Muriel"。 | H74: 密码是“Muiriel”。 | I74: Existing Sprint 52 machine translation, not written for this sprint. We only need your quality band and any errors you see. Expected: Password transliterated/misspelled (Muriel vs Muiriel) - the password becomes wrong. | L74: poor | M74: Yes | N74: poor | O74: n/a | P74: 密码是"Muriel" — 密码中的字符串与源文中的 “Muiriel” 不一致。 | Q74: 密码是“Muiriel”。 | S74: =IF(N74="","",IF(N74=L74,"agree","DISAGREE")) -> agree
A75: B::A_386::gold | B75: A_386 | C75: named_entity | D75: gold | E75: simplified | F75: Hangeul is the only purposely invented alphabet in popular daily use. The alphabet was invented in 1444 during the reign of King Sejong (1418 – 1450). | G75: 韩文字母是唯一一种特意发明、供日常使用的字母表，于1444年世宗大王（1418—1450年在位）统治时期创制。 | H75: 韩文字母是唯一一种特意发明、供日常使用的字母表，于1444年世宗大王（1418—1450年在位）统治时期创制。 | I75: PROPOSED REFERENCE. Should be a fully correct, natural Mainland Mandarin translation. If anything is wrong or unnatural, write a corrected sentence in column Q - it will become the reference for every row of this source. NOTE: Gold departs from the Sprint 50 reference, which says 世宗皇帝 ('Emperor'); Sejong was a king, conventionally 世宗大王. | L75: clean | M75: Yes | N75: clean | O75: n/a | S75: =IF(N75="","",IF(N75=L75,"agree","DISAGREE")) -> agree
A76: B::A_386::paraphrase | B76: A_386 | C76: named_entity | D76: paraphrase | E76: simplified | F76: Hangeul is the only purposely invented alphabet in popular daily use. The alphabet was invented in 1444 during the reign of King Sejong (1418 – 1450). | G76: 在日常生活中普遍使用的字母文字里，只有韩文是人为专门创造的；它诞生于1444年，当时朝鲜正处在世宗大王的统治之下（1418至1450年）。 | H76: 韩文字母是唯一一种特意发明、供日常使用的字母表，于1444年世宗大王（1418—1450年在位）统治时期创制。 | I76: Should mean EXACTLY the same as the gold row, using deliberately different wording. Check nothing is added, lost or changed, and that it sounds natural. | L76: clean | M76: Yes | N76: clean | O76: n/a | S76: =IF(N76="","",IF(N76=L76,"agree","DISAGREE")) -> agree
A77: B::A_386::literal | B77: A_386 | C77: named_entity | D77: literal | E77: simplified | F77: Hangeul is the only purposely invented alphabet in popular daily use. The alphabet was invented in 1444 during the reign of King Sejong (1418 – 1450). | G77: 韩文是唯一的被故意发明的字母在流行的日常使用中。这个字母被发明于1444年在世宗国王的统治期间（1418–1450）。 | H77: 韩文字母是唯一一种特意发明、供日常使用的字母表，于1444年世宗大王（1418—1450年在位）统治时期创制。 | I77: Should have NO meaning errors, but be stiff / word-for-word on purpose. Stiffness is intended - only flag meaning problems or ungrammatical Chinese. | L77: moderate | M77: Yes | N77: moderate | O77: n/a | S77: =IF(N77="","",IF(N77=L77,"agree","DISAGREE")) -> agree
A78: B::A_386::fluent_wrong | B78: A_386 | C78: named_entity | D78: fluent_wrong | E78: simplified | F78: Hangeul is the only purposely invented alphabet in popular daily use. The alphabet was invented in 1444 during the reign of King Sejong (1418 – 1450). | G78: 韩文字母是最早一种特意发明、供日常使用的字母表，于1444年世宗大王（1418—1450年在位）统治时期创制。 | H78: 韩文字母是唯一一种特意发明、供日常使用的字母表，于1444年世宗大王（1418—1450年在位）统治时期创制。 | I78: Should read naturally but contain exactly ONE planted meaning error (columns J-K). Check the error is real and that there is no OTHER error. | J78: 最早 | K78: [Mistranslation, major] 'The only' becomes 'the earliest'. | L78: poor | M78: Yes | N78: poor | O78: major | S78: =IF(N78="","",IF(N78=L78,"agree","DISAGREE")) -> agree
A79: B::A_386::targeted_error | B79: A_386 | C79: named_entity | D79: targeted_error | E79: simplified | F79: Hangeul is the only purposely invented alphabet in popular daily use. The alphabet was invented in 1444 during the reign of King Sejong (1418 – 1450). | G79: 韩文字母是唯一一种特意发明、供日常使用的字母表，于1444年世祖大王（1418—1450年在位）统治时期创制。 | H79: 韩文字母是唯一一种特意发明、供日常使用的字母表，于1444年世宗大王（1418—1450年在位）统治时期创制。 | I79: Contains exactly ONE planted error typical of this category (columns J-K). Check the error is real and that there is no OTHER error. | J79: 世祖大王 | K79: [Mistranslation, major] King Sejong (世宗) replaced by a different Joseon king (世祖). | L79: poor | M79: Yes | N79: poor | O79: major | S79: =IF(N79="","",IF(N79=L79,"agree","DISAGREE")) -> agree
A80: B::A_386::traditional_char | B80: A_386 | C80: named_entity | D80: traditional_char | E80: traditional_char | F80: Hangeul is the only purposely invented alphabet in popular daily use. The alphabet was invented in 1444 during the reign of King Sejong (1418 – 1450). | G80: 韓文字母是唯一一種特意發明、供日常使用的字母表，於1444年世宗大王（1418—1450年在位）統治時期創制。 | H80: 韩文字母是唯一一种特意发明、供日常使用的字母表，于1444年世宗大王（1418—1450年在位）统治时期创制。 | I80: Gold converted to Traditional CHARACTERS only - same words. Check the meaning is unchanged and characters look right (e.g. no wrong 裡/里 swaps in names). | L80: clean | M80: Yes | N80: clean | O80: n/a | S80: =IF(N80="","",IF(N80=L80,"agree","DISAGREE")) -> agree
A81: B::A_1106::gold | B81: A_1106 | C81: named_entity | D81: gold | E81: simplified | F81: Dr. Malar Balasubramanian, 29, was found in Blue Ash, Ohio, a suburb approximately 15 miles north of Cincinnati lying on the ground beside the road in a T-shirt and underwear in an apparently heavily medicated state. | G81: 29岁的马拉尔·巴拉苏布拉马尼安医生被发现躺在俄亥俄州布卢阿什的路边地上。布卢阿什是辛辛那提以北约15英里的一个郊区。被发现时，她身穿T恤和内裤，显然服用了大量药物。 | H81: 29岁的马拉尔·巴拉苏布拉马尼安医生被发现躺在俄亥俄州布卢阿什的路边地上。布卢阿什是辛辛那提以北约15英里的一个郊区。被发现时，她身穿T恤和内裤，显然服用了大量药物。 | I81: PROPOSED REFERENCE. Should be a fully correct, natural Mainland Mandarin translation. If anything is wrong or unnatural, write a corrected sentence in column Q - it will become the reference for every row of this source. NOTE: 'Dr.' is ambiguous (medical doctor vs PhD); gold follows the Sprint 50 reference (医生). | L81: clean | M81: Yes | N81: clean | O81: n/a | S81: =IF(N81="","",IF(N81=L81,"agree","DISAGREE")) -> agree
A82: B::A_1106::paraphrase | B82: A_1106 | C82: named_entity | D82: paraphrase | E82: simplified | F82: Dr. Malar Balasubramanian, 29, was found in Blue Ash, Ohio, a suburb approximately 15 miles north of Cincinnati lying on the ground beside the road in a T-shirt and underwear in an apparently heavily medicated state. | G82: 在辛辛那提北面约15英里的郊区——俄亥俄州布卢阿什，人们发现现年29岁的马拉尔·巴拉苏布拉马尼安医生倒卧在路旁，身上穿着T恤和内衣，看起来像是服用了大量药物。 | H82: 29岁的马拉尔·巴拉苏布拉马尼安医生被发现躺在俄亥俄州布卢阿什的路边地上。布卢阿什是辛辛那提以北约15英里的一个郊区。被发现时，她身穿T恤和内裤，显然服用了大量药物。 | I82: Should mean EXACTLY the same as the gold row, using deliberately different wording. Check nothing is added, lost or changed, and that it sounds natural. | L82: clean | M82: Yes | N82: clean | O82: n/a | S82: =IF(N82="","",IF(N82=L82,"agree","DISAGREE")) -> agree
A83: B::A_1106::literal | B83: A_1106 | C83: named_entity | D83: literal | E83: simplified | F83: Dr. Malar Balasubramanian, 29, was found in Blue Ash, Ohio, a suburb approximately 15 miles north of Cincinnati lying on the ground beside the road in a T-shirt and underwear in an apparently heavily medicated state. | G83: 马拉尔·巴拉苏布拉马尼安医生，29岁，被发现在布卢阿什，俄亥俄州，一个大约在辛辛那提北边15英里的郊区，躺在路旁边的地上，穿着一件T恤和内衣，处在一个显然被大量用药的状态中。 | H83: 29岁的马拉尔·巴拉苏布拉马尼安医生被发现躺在俄亥俄州布卢阿什的路边地上。布卢阿什是辛辛那提以北约15英里的一个郊区。被发现时，她身穿T恤和内裤，显然服用了大量药物。 | I83: Should have NO meaning errors, but be stiff / word-for-word on purpose. Stiffness is intended - only flag meaning problems or ungrammatical Chinese. | L83: moderate | M83: Yes | N83: moderate | O83: n/a | S83: =IF(N83="","",IF(N83=L83,"agree","DISAGREE")) -> agree
A84: B::A_1106::fluent_wrong | B84: A_1106 | C84: named_entity | D84: fluent_wrong | E84: simplified | F84: Dr. Malar Balasubramanian, 29, was found in Blue Ash, Ohio, a suburb approximately 15 miles north of Cincinnati lying on the ground beside the road in a T-shirt and underwear in an apparently heavily medicated state. | G84: 29岁的马拉尔·巴拉苏布拉马尼安医生被发现躺在俄亥俄州布卢阿什的路边地上。布卢阿什是辛辛那提以南约15英里的一个郊区。被发现时，她身穿T恤和内裤，显然服用了大量药物。 | H84: 29岁的马拉尔·巴拉苏布拉马尼安医生被发现躺在俄亥俄州布卢阿什的路边地上。布卢阿什是辛辛那提以北约15英里的一个郊区。被发现时，她身穿T恤和内裤，显然服用了大量药物。 | I84: Should read naturally but contain exactly ONE planted meaning error (columns J-K). Check the error is real and that there is no OTHER error. | J84: 以南 | K84: [Mistranslation, major] 'North of Cincinnati' becomes 'south of'. | L84: poor | M84: Yes | N84: poor | O84: major | S84: =IF(N84="","",IF(N84=L84,"agree","DISAGREE")) -> agree
A85: B::A_1106::targeted_error | B85: A_1106 | C85: named_entity | D85: targeted_error | E85: simplified | F85: Dr. Malar Balasubramanian, 29, was found in Blue Ash, Ohio, a suburb approximately 15 miles north of Cincinnati lying on the ground beside the road in a T-shirt and underwear in an apparently heavily medicated state. | G85: 29岁的马拉尔·巴拉苏布拉马尼安医生被发现躺在俄亥俄州蓝灰市的路边地上。蓝灰市是辛辛那提以北约15英里的一个郊区。被发现时，她身穿T恤和内裤，显然服用了大量药物。 | H85: 29岁的马拉尔·巴拉苏布拉马尼安医生被发现躺在俄亥俄州布卢阿什的路边地上。布卢阿什是辛辛那提以北约15英里的一个郊区。被发现时，她身穿T恤和内裤，显然服用了大量药物。 | I85: Contains exactly ONE planted error typical of this category (columns J-K). Check the error is real and that there is no OTHER error. | J85: 蓝灰市 | K85: [Mistranslation, major] Place name 'Blue Ash' translated word-by-word ('blue-grey city') instead of transliterated (same error as the Sprint 50 MT output). Appears twice. | L85: poor | M85: Yes | N85: poor | O85: major | S85: =IF(N85="","",IF(N85=L85,"agree","DISAGREE")) -> agree
A86: B::A_1106::traditional_char | B86: A_1106 | C86: named_entity | D86: traditional_char | E86: traditional_char | F86: Dr. Malar Balasubramanian, 29, was found in Blue Ash, Ohio, a suburb approximately 15 miles north of Cincinnati lying on the ground beside the road in a T-shirt and underwear in an apparently heavily medicated state. | G86: 29歲的馬拉爾·巴拉蘇布拉馬尼安醫生被發現躺在俄亥俄州布盧阿什的路邊地上。布盧阿什是辛辛那提以北約15英里的一個郊區。被發現時，她身穿T恤和內褲，顯然服用了大量藥物。 | H86: 29岁的马拉尔·巴拉苏布拉马尼安医生被发现躺在俄亥俄州布卢阿什的路边地上。布卢阿什是辛辛那提以北约15英里的一个郊区。被发现时，她身穿T恤和内裤，显然服用了大量药物。 | I86: Gold converted to Traditional CHARACTERS only - same words. Check the meaning is unchanged and characters look right (e.g. no wrong 裡/里 swaps in names). | L86: clean | M86: Yes | N86: clean | O86: n/a | S86: =IF(N86="","",IF(N86=L86,"agree","DISAGREE")) -> agree
A87: B::A_1106::traditional_tw | B87: A_1106 | C87: named_entity | D87: traditional_tw | E87: traditional_tw | F87: Dr. Malar Balasubramanian, 29, was found in Blue Ash, Ohio, a suburb approximately 15 miles north of Cincinnati lying on the ground beside the road in a T-shirt and underwear in an apparently heavily medicated state. | G87: 29歲的馬拉爾·巴拉蘇布拉馬尼安醫師被發現躺在俄亥俄州布盧阿什的路邊地上。布盧阿什是辛辛那提以北約15英里的一個郊區。被發現時，她身穿T恤和內褲，顯然服用了大量藥物。 | H87: 29岁的马拉尔·巴拉苏布拉马尼安医生被发现躺在俄亥俄州布卢阿什的路边地上。布卢阿什是辛辛那提以北约15英里的一个郊区。被发现时，她身穿T恤和内裤，显然服用了大量药物。 | I87: Gold adapted for Taiwan: Traditional characters + Taiwan vocabulary (e.g. 伺服器, 公尺, 財務長) + 「」 quotes. Check the meaning is unchanged. If you are unsure whether a word is natural in Taiwan, answer 'Not sure' in Q1 rather than guessing. | L87: clean | M87: Yes | N87: clean | O87: n/a | S87: =IF(N87="","",IF(N87=L87,"agree","DISAGREE")) -> agree
A88: B::A_1727::gold | B88: A_1727 | C88: named_entity | D88: gold | E88: simplified | F88: To get the best views of Hong Kong, leave the island and head for the Kowloon waterfront opposite. | G88: 若想从最佳角度欣赏香港的美景，可以离开香港岛，前往对面的九龙海滨。 | H88: 若想从最佳角度欣赏香港的美景，可以离开香港岛，前往对面的九龙海滨。 | I88: PROPOSED REFERENCE. Should be a fully correct, natural Mainland Mandarin translation. If anything is wrong or unnatural, write a corrected sentence in column Q - it will become the reference for every row of this source. | L88: clean | M88: Yes | N88: clean | O88: n/a | S88: =IF(N88="","",IF(N88=L88,"agree","DISAGREE")) -> agree
A89: B::A_1727::paraphrase | B89: A_1727 | C89: named_entity | D89: paraphrase | E89: simplified | F89: To get the best views of Hong Kong, leave the island and head for the Kowloon waterfront opposite. | G89: 想把香港景色尽收眼底，不妨离开港岛，到对岸的九龙海滨去。 | H89: 若想从最佳角度欣赏香港的美景，可以离开香港岛，前往对面的九龙海滨。 | I89: Should mean EXACTLY the same as the gold row, using deliberately different wording. Check nothing is added, lost or changed, and that it sounds natural. | L89: clean | M89: Yes | N89: clean | O89: n/a | S89: =IF(N89="","",IF(N89=L89,"agree","DISAGREE")) -> agree
A90: B::A_1727::literal | B90: A_1727 | C90: named_entity | D90: literal | E90: simplified | F90: To get the best views of Hong Kong, leave the island and head for the Kowloon waterfront opposite. | G90: 为了得到香港的最好的景色，离开这个岛并且前往对面的九龙海滨。 | H90: 若想从最佳角度欣赏香港的美景，可以离开香港岛，前往对面的九龙海滨。 | I90: Should have NO meaning errors, but be stiff / word-for-word on purpose. Stiffness is intended - only flag meaning problems or ungrammatical Chinese. | L90: moderate | M90: Yes | N90: moderate | O90: n/a | S90: =IF(N90="","",IF(N90=L90,"agree","DISAGREE")) -> agree
A91: B::A_1727::fluent_wrong | B91: A_1727 | C91: named_entity | D91: fluent_wrong | E91: simplified | F91: To get the best views of Hong Kong, leave the island and head for the Kowloon waterfront opposite. | G91: 若想从最佳角度欣赏香港的美景，可以离开香港岛，前往后方的九龙海滨。 | H91: 若想从最佳角度欣赏香港的美景，可以离开香港岛，前往对面的九龙海滨。 | I91: Should read naturally but contain exactly ONE planted meaning error (columns J-K). Check the error is real and that there is no OTHER error. | J91: 后方 | K91: [Mistranslation, major] Waterfront 'opposite' becomes 'behind'. | L91: poor | M91: Yes | N91: poor | O91: major | S91: =IF(N91="","",IF(N91=L91,"agree","DISAGREE")) -> agree
A92: B::A_1727::targeted_error | B92: A_1727 | C92: named_entity | D92: targeted_error | E92: simplified | F92: To get the best views of Hong Kong, leave the island and head for the Kowloon waterfront opposite. | G92: 若想从最佳角度欣赏香港的美景，可以离开香港岛，前往对面的科隆海滨。 | H92: 若想从最佳角度欣赏香港的美景，可以离开香港岛，前往对面的九龙海滨。 | I92: Contains exactly ONE planted error typical of this category (columns J-K). Check the error is real and that there is no OTHER error. | J92: 科隆 | K92: [Mistranslation, major] Kowloon rendered as 科隆 (Cologne) - same error as the Sprint 50 MT output. | L92: poor | M92: Yes | N92: poor | O92: major | S92: =IF(N92="","",IF(N92=L92,"agree","DISAGREE")) -> agree
A93: B::A_1727::traditional_char | B93: A_1727 | C93: named_entity | D93: traditional_char | E93: traditional_char | F93: To get the best views of Hong Kong, leave the island and head for the Kowloon waterfront opposite. | G93: 若想從最佳角度欣賞香港的美景，可以離開香港島，前往對面的九龍海濱。 | H93: 若想从最佳角度欣赏香港的美景，可以离开香港岛，前往对面的九龙海滨。 | I93: Gold converted to Traditional CHARACTERS only - same words. Check the meaning is unchanged and characters look right (e.g. no wrong 裡/里 swaps in names). | L93: clean | M93: Yes | N93: clean | O93: n/a | S93: =IF(N93="","",IF(N93=L93,"agree","DISAGREE")) -> agree
A94: B::A_126::gold | B94: A_126 | C94: named_entity | D94: gold | E94: simplified | F94: Since its inception, The Onion has become a veritable news parody empire, with a print edition, a website that drew 5,000,000 unique visitors in the month of October, personal ads, a 24 hour news network, podcasts, and a recently launched world atlas called Our Dumb World. | G94: 自创办以来，《洋葱报》已经成为一个名副其实的恶搞新闻帝国，旗下拥有印刷版、网站（10月份吸引了500万独立访客）、个人广告、24小时新闻网络、播客，以及近期推出的世界地图集《我们的愚蠢世界》。 | H94: 自创办以来，《洋葱报》已经成为一个名副其实的恶搞新闻帝国，旗下拥有印刷版、网站（10月份吸引了500万独立访客）、个人广告、24小时新闻网络、播客，以及近期推出的世界地图集《我们的愚蠢世界》。 | I94: PROPOSED REFERENCE. Should be a fully correct, natural Mainland Mandarin translation. If anything is wrong or unnatural, write a corrected sentence in column Q - it will become the reference for every row of this source. | L94: clean | M94: Yes | N94: clean | O94: n/a | S94: =IF(N94="","",IF(N94=L94,"agree","DISAGREE")) -> agree
A95: B::A_126::paraphrase | B95: A_126 | C95: named_entity | D95: paraphrase | E95: simplified | F95: Since its inception, The Onion has become a veritable news parody empire, with a print edition, a website that drew 5,000,000 unique visitors in the month of October, personal ads, a 24 hour news network, podcasts, and a recently launched world atlas called Our Dumb World. | G95: 《洋葱报》创刊至今，已发展成一个不折不扣的恶搞新闻王国：它既有纸质版，也有网站（仅10月就迎来了500万名独立访客），还经营征友广告、全天候新闻频道和播客，最近更推出了一本世界地图集，书名叫《我们的愚蠢世界》。 | H95: 自创办以来，《洋葱报》已经成为一个名副其实的恶搞新闻帝国，旗下拥有印刷版、网站（10月份吸引了500万独立访客）、个人广告、24小时新闻网络、播客，以及近期推出的世界地图集《我们的愚蠢世界》。 | I95: Should mean EXACTLY the same as the gold row, using deliberately different wording. Check nothing is added, lost or changed, and that it sounds natural. | L95: clean | M95: Yes | N95: clean | O95: n/a | S95: =IF(N95="","",IF(N95=L95,"agree","DISAGREE")) -> agree
A96: B::A_126::literal | B96: A_126 | C96: named_entity | D96: literal | E96: simplified | F96: Since its inception, The Onion has become a veritable news parody empire, with a print edition, a website that drew 5,000,000 unique visitors in the month of October, personal ads, a 24 hour news network, podcasts, and a recently launched world atlas called Our Dumb World. | G96: 自从它的开始，《洋葱报》已经变成了一个名副其实的新闻模仿帝国，带有一个印刷版、一个在十月份吸引了5,000,000个独立访问者的网站、个人广告、一个24小时新闻网络、播客，以及一个最近推出的叫作《我们的愚蠢世界》的世界地图集。 | H96: 自创办以来，《洋葱报》已经成为一个名副其实的恶搞新闻帝国，旗下拥有印刷版、网站（10月份吸引了500万独立访客）、个人广告、24小时新闻网络、播客，以及近期推出的世界地图集《我们的愚蠢世界》。 | I96: Should have NO meaning errors, but be stiff / word-for-word on purpose. Stiffness is intended - only flag meaning problems or ungrammatical Chinese. | L96: moderate | M96: Yes | N96: moderate | O96: n/a | S96: =IF(N96="","",IF(N96=L96,"agree","DISAGREE")) -> agree
A97: B::A_126::fluent_wrong | B97: A_126 | C97: named_entity | D97: fluent_wrong | E97: simplified | F97: Since its inception, The Onion has become a veritable news parody empire, with a print edition, a website that drew 5,000,000 unique visitors in the month of October, personal ads, a 24 hour news network, podcasts, and a recently launched world atlas called Our Dumb World. | G97: 自创办以来，《洋葱报》已经成为一个名副其实的恶搞新闻帝国，旗下拥有印刷版、网站（10月份吸引了5000万独立访客）、个人广告、24小时新闻网络、播客，以及近期推出的世界地图集《我们的愚蠢世界》。 | H97: 自创办以来，《洋葱报》已经成为一个名副其实的恶搞新闻帝国，旗下拥有印刷版、网站（10月份吸引了500万独立访客）、个人广告、24小时新闻网络、播客，以及近期推出的世界地图集《我们的愚蠢世界》。 | I97: Should read naturally but contain exactly ONE planted meaning error (columns J-K). Check the error is real and that there is no OTHER error. | J97: 5000万 | K97: [Mistranslation, major] 5,000,000 (500万) becomes 50,000,000 (5000万) - same error as the Sprint 50 MT output. | L97: poor | M97: Yes | N97: poor | O97: major | S97: =IF(N97="","",IF(N97=L97,"agree","DISAGREE")) -> agree
A98: B::A_126::targeted_error | B98: A_126 | C98: named_entity | D98: targeted_error | E98: simplified | F98: Since its inception, The Onion has become a veritable news parody empire, with a print edition, a website that drew 5,000,000 unique visitors in the month of October, personal ads, a 24 hour news network, podcasts, and a recently launched world atlas called Our Dumb World. | G98: 自创办以来，《洋葱圈》已经成为一个名副其实的恶搞新闻帝国，旗下拥有印刷版、网站（10月份吸引了500万独立访客）、个人广告、24小时新闻网络、播客，以及近期推出的世界地图集《我们的愚蠢世界》。 | H98: 自创办以来，《洋葱报》已经成为一个名副其实的恶搞新闻帝国，旗下拥有印刷版、网站（10月份吸引了500万独立访客）、个人广告、24小时新闻网络、播客，以及近期推出的世界地图集《我们的愚蠢世界》。 | I98: Contains exactly ONE planted error typical of this category (columns J-K). Check the error is real and that there is no OTHER error. | J98: 洋葱圈 | K98: [Mistranslation, major] Publication name 'The Onion' becomes 'Onion Rings'. | L98: poor | M98: Yes | N98: poor | O98: major | S98: =IF(N98="","",IF(N98=L98,"agree","DISAGREE")) -> agree
A99: B::A_126::traditional_char | B99: A_126 | C99: named_entity | D99: traditional_char | E99: traditional_char | F99: Since its inception, The Onion has become a veritable news parody empire, with a print edition, a website that drew 5,000,000 unique visitors in the month of October, personal ads, a 24 hour news network, podcasts, and a recently launched world atlas called Our Dumb World. | G99: 自創辦以來，《洋蔥報》已經成為一個名副其實的惡搞新聞帝國，旗下擁有印刷版、網站（10月份吸引了500萬獨立訪客）、個人廣告、24小時新聞網絡、播客，以及近期推出的世界地圖集《我們的愚蠢世界》。 | H99: 自创办以来，《洋葱报》已经成为一个名副其实的恶搞新闻帝国，旗下拥有印刷版、网站（10月份吸引了500万独立访客）、个人广告、24小时新闻网络、播客，以及近期推出的世界地图集《我们的愚蠢世界》。 | I99: Gold converted to Traditional CHARACTERS only - same words. Check the meaning is unchanged and characters look right (e.g. no wrong 裡/里 swaps in names). | L99: clean | M99: Yes | N99: clean | O99: n/a | S99: =IF(N99="","",IF(N99=L99,"agree","DISAGREE")) -> agree
A100: B::A_126::traditional_tw | B100: A_126 | C100: named_entity | D100: traditional_tw | E100: traditional_tw | F100: Since its inception, The Onion has become a veritable news parody empire, with a print edition, a website that drew 5,000,000 unique visitors in the month of October, personal ads, a 24 hour news network, podcasts, and a recently launched world atlas called Our Dumb World. | G100: 自創辦以來，《洋蔥報》已經成為一個名副其實的惡搞新聞帝國，旗下擁有印刷版、網站（10月份吸引了500萬名不重複訪客）、個人廣告、24小時新聞網路、Podcast，以及近期推出的世界地圖集《我們的愚蠢世界》。 | H100: 自创办以来，《洋葱报》已经成为一个名副其实的恶搞新闻帝国，旗下拥有印刷版、网站（10月份吸引了500万独立访客）、个人广告、24小时新闻网络、播客，以及近期推出的世界地图集《我们的愚蠢世界》。 | I100: Gold adapted for Taiwan: Traditional characters + Taiwan vocabulary (e.g. 伺服器, 公尺, 財務長) + 「」 quotes. Check the meaning is unchanged. If you are unsure whether a word is natural in Taiwan, answer 'Not sure' in Q1 rather than guessing. | L100: clean | M100: Yes | N100: clean | O100: n/a | S100: =IF(N100="","",IF(N100=L100,"agree","DISAGREE")) -> agree
...

Sheet Summary
A1: Review progress and agreement with our expected bands (all cells are formulas)
A3: Row type | B3: Rows | C3: Reviewed (Q2 filled) | D3: Band agrees | E3: Agreement rate
A4: gold | B4: =COUNTIF(Review!$D$2:$D$266,A4) -> 40 | C4: =COUNTIFS(Review!$D$2:$D$266,A4,Review!$N$2:$N$266,"<>") -> 40 | D4: =COUNTIFS(Review!$D$2:$D$266,A4,Review!$S$2:$S$266,"agree") -> 40 | E4: =IF(C4=0,"-",D4/C4) -> 1
A5: paraphrase | B5: =COUNTIF(Review!$D$2:$D$266,A5) -> 40 | C5: =COUNTIFS(Review!$D$2:$D$266,A5,Review!$N$2:$N$266,"<>") -> 40 | D5: =COUNTIFS(Review!$D$2:$D$266,A5,Review!$S$2:$S$266,"agree") -> 40 | E5: =IF(C5=0,"-",D5/C5) -> 1
A6: literal | B6: =COUNTIF(Review!$D$2:$D$266,A6) -> 40 | C6: =COUNTIFS(Review!$D$2:$D$266,A6,Review!$N$2:$N$266,"<>") -> 40 | D6: =COUNTIFS(Review!$D$2:$D$266,A6,Review!$S$2:$S$266,"agree") -> 40 | E6: =IF(C6=0,"-",D6/C6) -> 1
A7: padded | B7: =COUNTIF(Review!$D$2:$D$266,A7) -> 5 | C7: =COUNTIFS(Review!$D$2:$D$266,A7,Review!$N$2:$N$266,"<>") -> 5 | D7: =COUNTIFS(Review!$D$2:$D$266,A7,Review!$S$2:$S$266,"agree") -> 5 | E7: =IF(C7=0,"-",D7/C7) -> 1
A8: fluent_wrong | B8: =COUNTIF(Review!$D$2:$D$266,A8) -> 40 | C8: =COUNTIFS(Review!$D$2:$D$266,A8,Review!$N$2:$N$266,"<>") -> 40 | D8: =COUNTIFS(Review!$D$2:$D$266,A8,Review!$S$2:$S$266,"agree") -> 40 | E8: =IF(C8=0,"-",D8/C8) -> 1
A9: targeted_error | B9: =COUNTIF(Review!$D$2:$D$266,A9) -> 40 | C9: =COUNTIFS(Review!$D$2:$D$266,A9,Review!$N$2:$N$266,"<>") -> 40 | D9: =COUNTIFS(Review!$D$2:$D$266,A9,Review!$S$2:$S$266,"agree") -> 40 | E9: =IF(C9=0,"-",D9/C9) -> 1
A10: original_candidate | B10: =COUNTIF(Review!$D$2:$D$266,A10) -> 16 | C10: =COUNTIFS(Review!$D$2:$D$266,A10,Review!$N$2:$N$266,"<>") -> 16 | D10: =COUNTIFS(Review!$D$2:$D$266,A10,Review!$S$2:$S$266,"agree") -> 16 | E10: =IF(C10=0,"-",D10/C10) -> 1
A11: traditional_char | B11: =COUNTIF(Review!$D$2:$D$266,A11) -> 30 | C11: =COUNTIFS(Review!$D$2:$D$266,A11,Review!$N$2:$N$266,"<>") -> 30 | D11: =COUNTIFS(Review!$D$2:$D$266,A11,Review!$S$2:$S$266,"agree") -> 30 | E11: =IF(C11=0,"-",D11/C11) -> 1
A12: traditional_tw | B12: =COUNTIF(Review!$D$2:$D$266,A12) -> 14 | C12: =COUNTIFS(Review!$D$2:$D$266,A12,Review!$N$2:$N$266,"<>") -> 14 | D12: =COUNTIFS(Review!$D$2:$D$266,A12,Review!$S$2:$S$266,"agree") -> 14 | E12: =IF(C12=0,"-",D12/C12) -> 1
A13: TOTAL | B13: =SUM(B4:B12) -> 265 | C13: =SUM(C4:C12) -> 265 | D13: =SUM(D4:D12) -> 265 | E13: =IF(C13=0,"-",D13/C13) -> 1
A15: Q1 answered 'No' or 'Partly': | B15: =COUNTIF(Review!$M$2:$M$266,"No")+COUNTIF(Review!$M$2:$M$266,"Partly") -> 1
A16: Corrections suggested (Q5): | B16: =COUNTIF(Review!$Q$2:$Q$266,"?*") -> 6
